NanoPreP/__init__.py
NanoPreP/__main__.py
NanoPreP/_version.py
NanoPreP/html_report.py
NanoPreP/aligntools/__init__.py
NanoPreP/aligntools/edlibAligner.py
NanoPreP/optimize/__init__.py
NanoPreP/optimize/__main__.py
NanoPreP/optimize/argParser.py
NanoPreP/optimize/template.py
NanoPreP/paramtools/__init__.py
NanoPreP/paramtools/argParser.py
NanoPreP/paramtools/paramsets.py
NanoPreP/preptools/Annotator.py
NanoPreP/preptools/Optimizer.py
NanoPreP/preptools/Processor.py
NanoPreP/preptools/__init__.py
NanoPreP/preptools/polyFinder.py
NanoPreP/seqtools/FastqIO.py
NanoPreP/seqtools/SeqFastq.py
NanoPreP/seqtools/__init__.py
nanoprep_ffm-0.0.20.dist-info/licenses/LICENSE
nanoprep_ffm-0.0.20.dist-info/METADATA
nanoprep_ffm-0.0.20.dist-info/WHEEL
nanoprep_ffm-0.0.20.dist-info/entry_points.txt
nanoprep_ffm-0.0.20.dist-info/top_level.txt
nanoprep_ffm-0.0.20.dist-info/RECORD
